Metadata-Version: 1.1
Name: basiccalculatorpau
Version: 0.0.2
Summary: A very basic calculator
Home-page: UNKNOWN
Author: Pau Sanchez
Author-email: pausanchez.admifin@gmail.com
License: MIT
Keywords: calculator
Platform: UNKNOWN
Classifier: Development Status :: 5 - Production/Stable
Classifier: Intended Audience :: Education
Classifier: Operating System :: Unix
Classifier: Operating System :: MacOS :: MacOS X
Classifier: Operating System :: Microsoft :: Windows :: Windows 10
Classifier: License :: OSI Approved :: MIT License
Classifier: Programming Language :: Python :: 3
